{
  "kind": "collectionType",
  "collectionName": "members",
  "info": {
    "singularName": "member",
    "pluralName": "members",
    "displayName": "member",
    "description": ""
  },
  "options": {
    "draftAndPublish": true
  },
  "pluginOptions": {},
  "attributes": {
    "title": {
      "type": "string",
      "unique": true,
      "required": true
    },
    "paragraph": {
      "type": "text",
      "required": true,
      "unique": true
    },
    "image": {
      "type": "media",
      "multiple": false,
      "required": true,
      "allowedTypes": [
        "images"
      ]
    },
    "imgUrl": {
      "type": "string",
      "required": false,
      "unique": true
    }
  }
}
